cryptoolz/__init__.py
cryptoolz/base.py
cryptoolz/factory.py
cryptoolz/printer.py
cryptoolz/utils.py
cryptoolz/app/__init__.py
cryptoolz/app/cli/__init__.py
cryptoolz/app/cli/__main__.py
cryptoolz/app/cli/cryptoolz.py
cryptoolz/app/cli/keys.py
cryptoolz/app/cli/primes.py
cryptoolz/app/run/__init__.py
cryptoolz/app/run/dummies.py
cryptoolz/app/run/runner.py
cryptoolz/app/tools/__init__.py
cryptoolz/app/tools/base.py
cryptoolz/app/tools/keys/__init__.py
cryptoolz/app/tools/keys/base.py
cryptoolz/app/tools/keys/keys.py
cryptoolz/app/tools/keys/dropins/__init__.py
cryptoolz/app/tools/keys/dropins/eth.py
cryptoolz/crypto/__init__.py
cryptoolz/crypto/circuits.py
cryptoolz/crypto/constants.py
cryptoolz/crypto/data.py
cryptoolz/crypto/exceptions.py
cryptoolz/crypto/algorithms/base.py
cryptoolz/crypto/algorithms/shamir.py
cryptoolz/resources/primes_least_pow_two.json
cryptoolz-1.3.2.dist-info/AUTHORS.rst
cryptoolz-1.3.2.dist-info/LICENSE
cryptoolz-1.3.2.dist-info/METADATA
cryptoolz-1.3.2.dist-info/WHEEL
cryptoolz-1.3.2.dist-info/entry_points.txt
cryptoolz-1.3.2.dist-info/top_level.txt
cryptoolz-1.3.2.dist-info/RECORD
