Metadata-Version: 2.1
Name: cryptoolz
Version: 1.3.2
Summary: A small high-level crypto library / cli toolset.
Home-page: https://codeberg.com/tanats_nir/cryptoolz
Author: Tanats Nir
Author-email: tanats.nir@disroot.org
License: GNU General Public License v3
Classifier: License :: OSI Approved :: GNU General Public License v3 (GPLv3)
Classifier: Development Status :: 3 - Alpha
Classifier: Programming Language :: Python :: 3.11
Classifier: Natural Language :: English
Classifier: Topic :: Software Development :: Version Control :: Git
License-File: LICENSE
License-File: AUTHORS.rst
Requires-Dist: click
Requires-Dist: pydantic
Requires-Dist: cryptography
Requires-Dist: coincurve
Requires-Dist: eth-utils
Requires-Dist: eth-hash[pycryptodome]
Requires-Dist: segno
Provides-Extra: dev
Requires-Dist: build[virtualenv] ; extra == 'dev'
Requires-Dist: bump2version ; extra == 'dev'
Requires-Dist: wheel ; extra == 'dev'
Requires-Dist: watchdog ; extra == 'dev'
Requires-Dist: flake8 ; extra == 'dev'
Requires-Dist: tox ; extra == 'dev'
Requires-Dist: coverage ; extra == 'dev'
Requires-Dist: Sphinx ; extra == 'dev'
Requires-Dist: twine ; extra == 'dev'
Requires-Dist: black ; extra == 'dev'
Requires-Dist: mypy ; extra == 'dev'
